db_kirosake/__init__.py
db_kirosake/dbkirosake.py
db_kirosake-1.6.dist-info/LICENSE
db_kirosake-1.6.dist-info/METADATA
db_kirosake-1.6.dist-info/WHEEL
db_kirosake-1.6.dist-info/top_level.txt
db_kirosake-1.6.dist-info/RECORD
