Metadata-Version: 2.1
Name: db-kirosake
Version: 1.6
Summary: DataBase with GitHub Repo
Home-page: https://t1rxdqq.github.io
Author: t1rxdqq
Author-email: danilmerkulov63@gmail.com
License: UNKNOWN
Project-URL: Bug Tracker, https://github.com/t1rxdqq/db-kirosake-source/issues
Platform: UNKNOWN
Classifier: Programming Language :: Python :: 3
Classifier: License :: OSI Approved :: MIT License
Classifier: Operating System :: OS Independent
Requires-Python: >=3.6
License-File: LICENSE
